<annotation>
	<filename>01963.jpg</filename>
	<source>
		<database>DIOR</database>
	</source>
	<size>
		<width>800</width>
		<height>800</height>
		<depth>3</depth>
	</size>
	<segmented>0</segmented>
	<object>
		<name>airplane</name>
		<pose>Unspecified</pose>
		<bndbox>
			<xmin>19</xmin>
			<ymin>227</ymin>
			<xmax>200</xmax>
			<ymax>452</ymax>
		</bndbox>
	</object>
	<object>
		<name>airplane</name>
		<pose>Unspecified</pose>
		<bndbox>
			<xmin>529</xmin>
			<ymin>246</ymin>
			<xmax>595</xmax>
			<ymax>309</ymax>
		</bndbox>
	</object>
	<object>
		<name>airplane</name>
		<pose>Unspecified</pose>
		<bndbox>
			<xmin>533</xmin>
			<ymin>342</ymin>
			<xmax>597</xmax>
			<ymax>408</ymax>
		</bndbox>
	</object>
</annotation>
