<annotation>
	<filename>03108.jpg</filename>
	<source>
		<database>DIOR</database>
	</source>
	<size>
		<width>800</width>
		<height>800</height>
		<depth>3</depth>
	</size>
	<segmented>0</segmented>
	<object>
		<name>storagetank</name>
		<pose>Unspecified</pose>
		<bndbox>
			<xmin>261</xmin>
			<ymin>111</ymin>
			<xmax>329</xmax>
			<ymax>176</ymax>
		</bndbox>
	</object>
	<object>
		<name>vehicle</name>
		<pose>Unspecified</pose>
		<bndbox>
			<xmin>467</xmin>
			<ymin>303</ymin>
			<xmax>473</xmax>
			<ymax>313</ymax>
		</bndbox>
	</object>
	<object>
		<name>storagetank</name>
		<pose>Unspecified</pose>
		<bndbox>
			<xmin>356</xmin>
			<ymin>394</ymin>
			<xmax>432</xmax>
			<ymax>474</ymax>
		</bndbox>
	</object>
	<object>
		<name>storagetank</name>
		<pose>Unspecified</pose>
		<bndbox>
			<xmin>325</xmin>
			<ymin>500</ymin>
			<xmax>406</xmax>
			<ymax>581</ymax>
		</bndbox>
	</object>
	<object>
		<name>storagetank</name>
		<pose>Unspecified</pose>
		<bndbox>
			<xmin>291</xmin>
			<ymin>332</ymin>
			<xmax>344</xmax>
			<ymax>387</ymax>
		</bndbox>
	</object>
</annotation>
