<annotation>
	<filename>05331.jpg</filename>
	<source>
		<database>DIOR</database>
	</source>
	<size>
		<width>800</width>
		<height>800</height>
		<depth>3</depth>
	</size>
	<segmented>0</segmented>
	<object>
		<name>windmill</name>
		<pose>Unspecified</pose>
		<bndbox>
			<xmin>509</xmin>
			<ymin>139</ymin>
			<xmax>594</xmax>
			<ymax>199</ymax>
		</bndbox>
	</object>
	<object>
		<name>windmill</name>
		<pose>Unspecified</pose>
		<bndbox>
			<xmin>119</xmin>
			<ymin>609</ymin>
			<xmax>175</xmax>
			<ymax>669</ymax>
		</bndbox>
	</object>
	<object>
		<name>windmill</name>
		<pose>Unspecified</pose>
		<bndbox>
			<xmin>661</xmin>
			<ymin>555</ymin>
			<xmax>725</xmax>
			<ymax>613</ymax>
		</bndbox>
	</object>
</annotation>
