<annotation>
	<filename>06431.jpg</filename>
	<source>
		<database>DIOR</database>
	</source>
	<size>
		<width>800</width>
		<height>800</height>
		<depth>3</depth>
	</size>
	<segmented>0</segmented>
	<object>
		<name>harbor</name>
		<pose>Unspecified</pose>
		<bndbox>
			<xmin>39</xmin>
			<ymin>322</ymin>
			<xmax>658</xmax>
			<ymax>507</ymax>
		</bndbox>
	</object>
	<object>
		<name>harbor</name>
		<pose>Unspecified</pose>
		<bndbox>
			<xmin>37</xmin>
			<ymin>50</ymin>
			<xmax>654</xmax>
			<ymax>224</ymax>
		</bndbox>
	</object>
	<object>
		<name>harbor</name>
		<pose>Unspecified</pose>
		<bndbox>
			<xmin>57</xmin>
			<ymin>595</ymin>
			<xmax>659</xmax>
			<ymax>735</ymax>
		</bndbox>
	</object>
	<object>
		<name>ship</name>
		<pose>Unspecified</pose>
		<bndbox>
			<xmin>50</xmin>
			<ymin>68</ymin>
			<xmax>68</xmax>
			<ymax>130</ymax>
		</bndbox>
	</object>
	<object>
		<name>ship</name>
		<pose>Unspecified</pose>
		<bndbox>
			<xmin>104</xmin>
			<ymin>62</ymin>
			<xmax>122</xmax>
			<ymax>124</ymax>
		</bndbox>
	</object>
	<object>
		<name>ship</name>
		<pose>Unspecified</pose>
		<bndbox>
			<xmin>190</xmin>
			<ymin>70</ymin>
			<xmax>209</xmax>
			<ymax>126</ymax>
		</bndbox>
	</object>
	<object>
		<name>ship</name>
		<pose>Unspecified</pose>
		<bndbox>
			<xmin>266</xmin>
			<ymin>55</ymin>
			<xmax>296</xmax>
			<ymax>121</ymax>
		</bndbox>
	</object>
	<object>
		<name>ship</name>
		<pose>Unspecified</pose>
		<bndbox>
			<xmin>327</xmin>
			<ymin>59</ymin>
			<xmax>350</xmax>
			<ymax>117</ymax>
		</bndbox>
	</object>
	<object>
		<name>ship</name>
		<pose>Unspecified</pose>
		<bndbox>
			<xmin>358</xmin>
			<ymin>68</ymin>
			<xmax>379</xmax>
			<ymax>119</ymax>
		</bndbox>
	</object>
	<object>
		<name>ship</name>
		<pose>Unspecified</pose>
		<bndbox>
			<xmin>505</xmin>
			<ymin>49</ymin>
			<xmax>528</xmax>
			<ymax>117</ymax>
		</bndbox>
	</object>
	<object>
		<name>ship</name>
		<pose>Unspecified</pose>
		<bndbox>
			<xmin>542</xmin>
			<ymin>59</ymin>
			<xmax>565</xmax>
			<ymax>113</ymax>
		</bndbox>
	</object>
	<object>
		<name>ship</name>
		<pose>Unspecified</pose>
		<bndbox>
			<xmin>68</xmin>
			<ymin>149</ymin>
			<xmax>97</xmax>
			<ymax>222</ymax>
		</bndbox>
	</object>
	<object>
		<name>ship</name>
		<pose>Unspecified</pose>
		<bndbox>
			<xmin>107</xmin>
			<ymin>146</ymin>
			<xmax>123</xmax>
			<ymax>196</ymax>
		</bndbox>
	</object>
	<object>
		<name>ship</name>
		<pose>Unspecified</pose>
		<bndbox>
			<xmin>136</xmin>
			<ymin>147</ymin>
			<xmax>154</xmax>
			<ymax>202</ymax>
		</bndbox>
	</object>
	<object>
		<name>ship</name>
		<pose>Unspecified</pose>
		<bndbox>
			<xmin>217</xmin>
			<ymin>148</ymin>
			<xmax>240</xmax>
			<ymax>203</ymax>
		</bndbox>
	</object>
	<object>
		<name>ship</name>
		<pose>Unspecified</pose>
		<bndbox>
			<xmin>244</xmin>
			<ymin>148</ymin>
			<xmax>267</xmax>
			<ymax>203</ymax>
		</bndbox>
	</object>
	<object>
		<name>ship</name>
		<pose>Unspecified</pose>
		<bndbox>
			<xmin>301</xmin>
			<ymin>142</ymin>
			<xmax>324</xmax>
			<ymax>197</ymax>
		</bndbox>
	</object>
	<object>
		<name>ship</name>
		<pose>Unspecified</pose>
		<bndbox>
			<xmin>327</xmin>
			<ymin>145</ymin>
			<xmax>348</xmax>
			<ymax>190</ymax>
		</bndbox>
	</object>
	<object>
		<name>ship</name>
		<pose>Unspecified</pose>
		<bndbox>
			<xmin>388</xmin>
			<ymin>141</ymin>
			<xmax>410</xmax>
			<ymax>195</ymax>
		</bndbox>
	</object>
	<object>
		<name>ship</name>
		<pose>Unspecified</pose>
		<bndbox>
			<xmin>547</xmin>
			<ymin>138</ymin>
			<xmax>569</xmax>
			<ymax>192</ymax>
		</bndbox>
	</object>
	<object>
		<name>ship</name>
		<pose>Unspecified</pose>
		<bndbox>
			<xmin>74</xmin>
			<ymin>324</ymin>
			<xmax>105</xmax>
			<ymax>418</ymax>
		</bndbox>
	</object>
	<object>
		<name>ship</name>
		<pose>Unspecified</pose>
		<bndbox>
			<xmin>142</xmin>
			<ymin>350</ymin>
			<xmax>171</xmax>
			<ymax>422</ymax>
		</bndbox>
	</object>
	<object>
		<name>ship</name>
		<pose>Unspecified</pose>
		<bndbox>
			<xmin>177</xmin>
			<ymin>326</ymin>
			<xmax>207</xmax>
			<ymax>416</ymax>
		</bndbox>
	</object>
	<object>
		<name>ship</name>
		<pose>Unspecified</pose>
		<bndbox>
			<xmin>245</xmin>
			<ymin>345</ymin>
			<xmax>269</xmax>
			<ymax>418</ymax>
		</bndbox>
	</object>
	<object>
		<name>ship</name>
		<pose>Unspecified</pose>
		<bndbox>
			<xmin>283</xmin>
			<ymin>336</ymin>
			<xmax>307</xmax>
			<ymax>413</ymax>
		</bndbox>
	</object>
	<object>
		<name>ship</name>
		<pose>Unspecified</pose>
		<bndbox>
			<xmin>349</xmin>
			<ymin>338</ymin>
			<xmax>374</xmax>
			<ymax>411</ymax>
		</bndbox>
	</object>
	<object>
		<name>ship</name>
		<pose>Unspecified</pose>
		<bndbox>
			<xmin>380</xmin>
			<ymin>331</ymin>
			<xmax>407</xmax>
			<ymax>413</ymax>
		</bndbox>
	</object>
	<object>
		<name>ship</name>
		<pose>Unspecified</pose>
		<bndbox>
			<xmin>411</xmin>
			<ymin>327</ymin>
			<xmax>439</xmax>
			<ymax>409</ymax>
		</bndbox>
	</object>
	<object>
		<name>ship</name>
		<pose>Unspecified</pose>
		<bndbox>
			<xmin>446</xmin>
			<ymin>330</ymin>
			<xmax>472</xmax>
			<ymax>409</ymax>
		</bndbox>
	</object>
	<object>
		<name>ship</name>
		<pose>Unspecified</pose>
		<bndbox>
			<xmin>481</xmin>
			<ymin>337</ymin>
			<xmax>508</xmax>
			<ymax>411</ymax>
		</bndbox>
	</object>
	<object>
		<name>ship</name>
		<pose>Unspecified</pose>
		<bndbox>
			<xmin>519</xmin>
			<ymin>344</ymin>
			<xmax>541</xmax>
			<ymax>410</ymax>
		</bndbox>
	</object>
	<object>
		<name>ship</name>
		<pose>Unspecified</pose>
		<bndbox>
			<xmin>41</xmin>
			<ymin>419</ymin>
			<xmax>68</xmax>
			<ymax>500</ymax>
		</bndbox>
	</object>
	<object>
		<name>ship</name>
		<pose>Unspecified</pose>
		<bndbox>
			<xmin>86</xmin>
			<ymin>441</ymin>
			<xmax>108</xmax>
			<ymax>507</ymax>
		</bndbox>
	</object>
	<object>
		<name>ship</name>
		<pose>Unspecified</pose>
		<bndbox>
			<xmin>117</xmin>
			<ymin>438</ymin>
			<xmax>143</xmax>
			<ymax>511</ymax>
		</bndbox>
	</object>
	<object>
		<name>ship</name>
		<pose>Unspecified</pose>
		<bndbox>
			<xmin>180</xmin>
			<ymin>436</ymin>
			<xmax>203</xmax>
			<ymax>503</ymax>
		</bndbox>
	</object>
	<object>
		<name>ship</name>
		<pose>Unspecified</pose>
		<bndbox>
			<xmin>212</xmin>
			<ymin>437</ymin>
			<xmax>237</xmax>
			<ymax>492</ymax>
		</bndbox>
	</object>
	<object>
		<name>ship</name>
		<pose>Unspecified</pose>
		<bndbox>
			<xmin>243</xmin>
			<ymin>437</ymin>
			<xmax>270</xmax>
			<ymax>503</ymax>
		</bndbox>
	</object>
	<object>
		<name>ship</name>
		<pose>Unspecified</pose>
		<bndbox>
			<xmin>306</xmin>
			<ymin>437</ymin>
			<xmax>331</xmax>
			<ymax>500</ymax>
		</bndbox>
	</object>
	<object>
		<name>ship</name>
		<pose>Unspecified</pose>
		<bndbox>
			<xmin>334</xmin>
			<ymin>433</ymin>
			<xmax>361</xmax>
			<ymax>503</ymax>
		</bndbox>
	</object>
	<object>
		<name>ship</name>
		<pose>Unspecified</pose>
		<bndbox>
			<xmin>431</xmin>
			<ymin>436</ymin>
			<xmax>452</xmax>
			<ymax>500</ymax>
		</bndbox>
	</object>
	<object>
		<name>ship</name>
		<pose>Unspecified</pose>
		<bndbox>
			<xmin>460</xmin>
			<ymin>429</ymin>
			<xmax>486</xmax>
			<ymax>501</ymax>
		</bndbox>
	</object>
	<object>
		<name>ship</name>
		<pose>Unspecified</pose>
		<bndbox>
			<xmin>518</xmin>
			<ymin>432</ymin>
			<xmax>551</xmax>
			<ymax>497</ymax>
		</bndbox>
	</object>
	<object>
		<name>ship</name>
		<pose>Unspecified</pose>
		<bndbox>
			<xmin>560</xmin>
			<ymin>427</ymin>
			<xmax>582</xmax>
			<ymax>487</ymax>
		</bndbox>
	</object>
	<object>
		<name>ship</name>
		<pose>Unspecified</pose>
		<bndbox>
			<xmin>592</xmin>
			<ymin>435</ymin>
			<xmax>607</xmax>
			<ymax>477</ymax>
		</bndbox>
	</object>
	<object>
		<name>ship</name>
		<pose>Unspecified</pose>
		<bndbox>
			<xmin>57</xmin>
			<ymin>610</ymin>
			<xmax>77</xmax>
			<ymax>664</ymax>
		</bndbox>
	</object>
	<object>
		<name>ship</name>
		<pose>Unspecified</pose>
		<bndbox>
			<xmin>60</xmin>
			<ymin>677</ymin>
			<xmax>75</xmax>
			<ymax>727</ymax>
		</bndbox>
	</object>
	<object>
		<name>ship</name>
		<pose>Unspecified</pose>
		<bndbox>
			<xmin>86</xmin>
			<ymin>683</ymin>
			<xmax>104</xmax>
			<ymax>737</ymax>
		</bndbox>
	</object>
	<object>
		<name>ship</name>
		<pose>Unspecified</pose>
		<bndbox>
			<xmin>113</xmin>
			<ymin>683</ymin>
			<xmax>132</xmax>
			<ymax>727</ymax>
		</bndbox>
	</object>
	<object>
		<name>ship</name>
		<pose>Unspecified</pose>
		<bndbox>
			<xmin>139</xmin>
			<ymin>678</ymin>
			<xmax>153</xmax>
			<ymax>722</ymax>
		</bndbox>
	</object>
	<object>
		<name>ship</name>
		<pose>Unspecified</pose>
		<bndbox>
			<xmin>161</xmin>
			<ymin>606</ymin>
			<xmax>179</xmax>
			<ymax>653</ymax>
		</bndbox>
	</object>
	<object>
		<name>ship</name>
		<pose>Unspecified</pose>
		<bndbox>
			<xmin>186</xmin>
			<ymin>679</ymin>
			<xmax>208</xmax>
			<ymax>719</ymax>
		</bndbox>
	</object>
	<object>
		<name>ship</name>
		<pose>Unspecified</pose>
		<bndbox>
			<xmin>216</xmin>
			<ymin>673</ymin>
			<xmax>234</xmax>
			<ymax>717</ymax>
		</bndbox>
	</object>
	<object>
		<name>ship</name>
		<pose>Unspecified</pose>
		<bndbox>
			<xmin>268</xmin>
			<ymin>611</ymin>
			<xmax>281</xmax>
			<ymax>653</ymax>
		</bndbox>
	</object>
	<object>
		<name>ship</name>
		<pose>Unspecified</pose>
		<bndbox>
			<xmin>316</xmin>
			<ymin>674</ymin>
			<xmax>336</xmax>
			<ymax>727</ymax>
		</bndbox>
	</object>
	<object>
		<name>ship</name>
		<pose>Unspecified</pose>
		<bndbox>
			<xmin>344</xmin>
			<ymin>676</ymin>
			<xmax>360</xmax>
			<ymax>718</ymax>
		</bndbox>
	</object>
	<object>
		<name>ship</name>
		<pose>Unspecified</pose>
		<bndbox>
			<xmin>364</xmin>
			<ymin>671</ymin>
			<xmax>386</xmax>
			<ymax>732</ymax>
		</bndbox>
	</object>
	<object>
		<name>ship</name>
		<pose>Unspecified</pose>
		<bndbox>
			<xmin>363</xmin>
			<ymin>606</ymin>
			<xmax>381</xmax>
			<ymax>650</ymax>
		</bndbox>
	</object>
	<object>
		<name>ship</name>
		<pose>Unspecified</pose>
		<bndbox>
			<xmin>392</xmin>
			<ymin>611</ymin>
			<xmax>410</xmax>
			<ymax>653</ymax>
		</bndbox>
	</object>
	<object>
		<name>ship</name>
		<pose>Unspecified</pose>
		<bndbox>
			<xmin>416</xmin>
			<ymin>612</ymin>
			<xmax>434</xmax>
			<ymax>654</ymax>
		</bndbox>
	</object>
	<object>
		<name>ship</name>
		<pose>Unspecified</pose>
		<bndbox>
			<xmin>471</xmin>
			<ymin>605</ymin>
			<xmax>489</xmax>
			<ymax>647</ymax>
		</bndbox>
	</object>
	<object>
		<name>ship</name>
		<pose>Unspecified</pose>
		<bndbox>
			<xmin>493</xmin>
			<ymin>606</ymin>
			<xmax>511</xmax>
			<ymax>648</ymax>
		</bndbox>
	</object>
	<object>
		<name>ship</name>
		<pose>Unspecified</pose>
		<bndbox>
			<xmin>545</xmin>
			<ymin>613</ymin>
			<xmax>561</xmax>
			<ymax>649</ymax>
		</bndbox>
	</object>
	<object>
		<name>ship</name>
		<pose>Unspecified</pose>
		<bndbox>
			<xmin>568</xmin>
			<ymin>596</ymin>
			<xmax>590</xmax>
			<ymax>655</ymax>
		</bndbox>
	</object>
	<object>
		<name>ship</name>
		<pose>Unspecified</pose>
		<bndbox>
			<xmin>544</xmin>
			<ymin>671</ymin>
			<xmax>560</xmax>
			<ymax>716</ymax>
		</bndbox>
	</object>
	<object>
		<name>ship</name>
		<pose>Unspecified</pose>
		<bndbox>
			<xmin>573</xmin>
			<ymin>667</ymin>
			<xmax>589</xmax>
			<ymax>712</ymax>
		</bndbox>
	</object>
	<object>
		<name>ship</name>
		<pose>Unspecified</pose>
		<bndbox>
			<xmin>519</xmin>
			<ymin>671</ymin>
			<xmax>539</xmax>
			<ymax>729</ymax>
		</bndbox>
	</object>
	<object>
		<name>ship</name>
		<pose>Unspecified</pose>
		<bndbox>
			<xmin>498</xmin>
			<ymin>676</ymin>
			<xmax>516</xmax>
			<ymax>711</ymax>
		</bndbox>
	</object>
	<object>
		<name>ship</name>
		<pose>Unspecified</pose>
		<bndbox>
			<xmin>467</xmin>
			<ymin>669</ymin>
			<xmax>487</xmax>
			<ymax>716</ymax>
		</bndbox>
	</object>
	<object>
		<name>ship</name>
		<pose>Unspecified</pose>
		<bndbox>
			<xmin>442</xmin>
			<ymin>668</ymin>
			<xmax>462</xmax>
			<ymax>715</ymax>
		</bndbox>
	</object>
	<object>
		<name>ship</name>
		<pose>Unspecified</pose>
		<bndbox>
			<xmin>418</xmin>
			<ymin>670</ymin>
			<xmax>438</xmax>
			<ymax>717</ymax>
		</bndbox>
	</object>
	<object>
		<name>ship</name>
		<pose>Unspecified</pose>
		<bndbox>
			<xmin>391</xmin>
			<ymin>672</ymin>
			<xmax>411</xmax>
			<ymax>719</ymax>
		</bndbox>
	</object>
</annotation>
