<annotation>
	<filename>10763.jpg</filename>
	<source>
		<database>DIOR</database>
	</source>
	<size>
		<width>800</width>
		<height>800</height>
		<depth>3</depth>
	</size>
	<segmented>0</segmented>
	<object>
		<name>stadium</name>
		<pose>Unspecified</pose>
		<bndbox>
			<xmin>299</xmin>
			<ymin>231</ymin>
			<xmax>514</xmax>
			<ymax>497</ymax>
		</bndbox>
	</object>
	<object>
		<name>tenniscourt</name>
		<pose>Unspecified</pose>
		<bndbox>
			<xmin>392</xmin>
			<ymin>616</ymin>
			<xmax>411</xmax>
			<ymax>658</ymax>
		</bndbox>
	</object>
	<object>
		<name>tenniscourt</name>
		<pose>Unspecified</pose>
		<bndbox>
			<xmin>424</xmin>
			<ymin>615</ymin>
			<xmax>444</xmax>
			<ymax>658</ymax>
		</bndbox>
	</object>
	<object>
		<name>groundtrackfield</name>
		<pose>Unspecified</pose>
		<bndbox>
			<xmin>350</xmin>
			<ymin>264</ymin>
			<xmax>454</xmax>
			<ymax>459</ymax>
		</bndbox>
	</object>
</annotation>
