<annotation>
	<filename>13490.jpg</filename>
	<source>
		<database>DIOR</database>
	</source>
	<size>
		<width>800</width>
		<height>800</height>
		<depth>3</depth>
	</size>
	<segmented>0</segmented>
	<object>
		<name>ship</name>
		<pose>Unspecified</pose>
		<bndbox>
			<xmin>604</xmin>
			<ymin>8</ymin>
			<xmax>643</xmax>
			<ymax>29</ymax>
		</bndbox>
	</object>
	<object>
		<name>ship</name>
		<pose>Unspecified</pose>
		<bndbox>
			<xmin>201</xmin>
			<ymin>75</ymin>
			<xmax>216</xmax>
			<ymax>86</ymax>
		</bndbox>
	</object>
	<object>
		<name>ship</name>
		<pose>Unspecified</pose>
		<bndbox>
			<xmin>326</xmin>
			<ymin>107</ymin>
			<xmax>361</xmax>
			<ymax>129</ymax>
		</bndbox>
	</object>
	<object>
		<name>ship</name>
		<pose>Unspecified</pose>
		<bndbox>
			<xmin>404</xmin>
			<ymin>81</ymin>
			<xmax>421</xmax>
			<ymax>92</ymax>
		</bndbox>
	</object>
	<object>
		<name>ship</name>
		<pose>Unspecified</pose>
		<bndbox>
			<xmin>364</xmin>
			<ymin>201</ymin>
			<xmax>394</xmax>
			<ymax>220</ymax>
		</bndbox>
	</object>
	<object>
		<name>ship</name>
		<pose>Unspecified</pose>
		<bndbox>
			<xmin>449</xmin>
			<ymin>162</ymin>
			<xmax>479</xmax>
			<ymax>182</ymax>
		</bndbox>
	</object>
	<object>
		<name>ship</name>
		<pose>Unspecified</pose>
		<bndbox>
			<xmin>546</xmin>
			<ymin>207</ymin>
			<xmax>581</xmax>
			<ymax>230</ymax>
		</bndbox>
	</object>
	<object>
		<name>ship</name>
		<pose>Unspecified</pose>
		<bndbox>
			<xmin>693</xmin>
			<ymin>353</ymin>
			<xmax>710</xmax>
			<ymax>368</ymax>
		</bndbox>
	</object>
</annotation>
