<annotation>
	<filename>17381.jpg</filename>
	<source>
		<database>DIOR</database>
	</source>
	<size>
		<width>800</width>
		<height>800</height>
		<depth>3</depth>
	</size>
	<segmented>0</segmented>
	<object>
		<name>windmill</name>
		<pose>Unspecified</pose>
		<bndbox>
			<xmin>676</xmin>
			<ymin>237</ymin>
			<xmax>715</xmax>
			<ymax>291</ymax>
		</bndbox>
	</object>
	<object>
		<name>windmill</name>
		<pose>Unspecified</pose>
		<bndbox>
			<xmin>292</xmin>
			<ymin>393</ymin>
			<xmax>336</xmax>
			<ymax>439</ymax>
		</bndbox>
	</object>
	<object>
		<name>windmill</name>
		<pose>Unspecified</pose>
		<bndbox>
			<xmin>644</xmin>
			<ymin>599</ymin>
			<xmax>696</xmax>
			<ymax>659</ymax>
		</bndbox>
	</object>
</annotation>
