<annotation>
	<filename>18529.jpg</filename>
	<source>
		<database>DIOR</database>
	</source>
	<size>
		<width>800</width>
		<height>800</height>
		<depth>3</depth>
	</size>
	<segmented>0</segmented>
	<object>
		<name>chimney</name>
		<pose>Unspecified</pose>
		<bndbox>
			<xmin>268</xmin>
			<ymin>206</ymin>
			<xmax>380</xmax>
			<ymax>345</ymax>
		</bndbox>
	</object>
	<object>
		<name>chimney</name>
		<pose>Unspecified</pose>
		<bndbox>
			<xmin>260</xmin>
			<ymin>499</ymin>
			<xmax>422</xmax>
			<ymax>692</ymax>
		</bndbox>
	</object>
	<object>
		<name>storagetank</name>
		<pose>Unspecified</pose>
		<bndbox>
			<xmin>96</xmin>
			<ymin>346</ymin>
			<xmax>138</xmax>
			<ymax>391</ymax>
		</bndbox>
	</object>
	<object>
		<name>storagetank</name>
		<pose>Unspecified</pose>
		<bndbox>
			<xmin>134</xmin>
			<ymin>331</ymin>
			<xmax>165</xmax>
			<ymax>365</ymax>
		</bndbox>
	</object>
	<object>
		<name>vehicle</name>
		<pose>Unspecified</pose>
		<bndbox>
			<xmin>529</xmin>
			<ymin>96</ymin>
			<xmax>541</xmax>
			<ymax>119</ymax>
		</bndbox>
	</object>
</annotation>
