<?xml version="1.0" encoding="UTF-8"?>
<annotation>
    <folder>/JPEGImages-trainval.zip/JPEGImages-trainval/JPEGImages-trainval</folder>
    <filename>01544.jpg</filename>
    <path>/JPEGImages-trainval.zip/JPEGImages-trainval/JPEGImages-trainval</path>
    <source>
        <database>Unknown</database>
    </source>
    <size>
        <width>800</width>
        <height>800</height>
        <depth>3</depth>
    </size>
    <segmented>0</segmented>
    <object>
        <type>robndbox</type>
        <name>harbor</name>
        <pose>Unspecified</pose>
        <truncated>0</truncated>
        <difficult>0</difficult>
        <robndbox>
            <x_left_top>255</x_left_top>
            <y_left_top>45</y_left_top>
            <x_right_top>320</x_right_top>
            <y_right_top>45</y_right_top>
            <x_right_bottom>320</x_right_bottom>
            <y_right_bottom>215</y_right_bottom>
            <x_left_bottom>255</x_left_bottom>
            <y_left_bottom>215</y_left_bottom>
        </robndbox>
        <angle>0</angle>
    </object>
    <object>
        <type>robndbox</type>
        <name>harbor</name>
        <pose>Unspecified</pose>
        <truncated>0</truncated>
        <difficult>0</difficult>
        <robndbox>
            <x_left_top>564</x_left_top>
            <y_left_top>0</y_left_top>
            <x_right_top>652</x_right_top>
            <y_right_top>0</y_right_top>
            <x_right_bottom>652</x_right_bottom>
            <y_right_bottom>278</y_right_bottom>
            <x_left_bottom>564</x_left_bottom>
            <y_left_bottom>278</y_left_bottom>
        </robndbox>
        <angle>0</angle>
    </object>
    <object>
        <type>robndbox</type>
        <name>ship</name>
        <pose>Unspecified</pose>
        <truncated>0</truncated>
        <difficult>0</difficult>
        <robndbox>
            <x_left_top>410</x_left_top>
            <y_left_top>160</y_left_top>
            <x_right_top>428</x_right_top>
            <y_right_top>160</y_right_top>
            <x_right_bottom>428</x_right_bottom>
            <y_right_bottom>218</y_right_bottom>
            <x_left_bottom>410</x_left_bottom>
            <y_left_bottom>218</y_left_bottom>
        </robndbox>
        <angle>0</angle>
    </object>
    <object>
        <type>robndbox</type>
        <name>ship</name>
        <pose>Unspecified</pose>
        <truncated>0</truncated>
        <difficult>0</difficult>
        <robndbox>
            <x_left_top>439</x_left_top>
            <y_left_top>141</y_left_top>
            <x_right_top>467</x_right_top>
            <y_right_top>141</y_right_top>
            <x_right_bottom>467</x_right_bottom>
            <y_right_bottom>153</y_right_bottom>
            <x_left_bottom>439</x_left_bottom>
            <y_left_bottom>153</y_left_bottom>
        </robndbox>
        <angle>0</angle>
    </object>
    <object>
        <type>robndbox</type>
        <name>ship</name>
        <pose>Unspecified</pose>
        <truncated>0</truncated>
        <difficult>0</difficult>
        <robndbox>
            <x_left_top>573</x_left_top>
            <y_left_top>119</y_left_top>
            <x_right_top>605</x_right_top>
            <y_right_top>119</y_right_top>
            <x_right_bottom>605</x_right_bottom>
            <y_right_bottom>131</y_right_bottom>
            <x_left_bottom>573</x_left_bottom>
            <y_left_bottom>131</y_left_bottom>
        </robndbox>
        <angle>0</angle>
    </object>
    <object>
        <type>robndbox</type>
        <name>ship</name>
        <pose>Unspecified</pose>
        <truncated>0</truncated>
        <difficult>0</difficult>
        <robndbox>
            <x_left_top>568</x_left_top>
            <y_left_top>136</y_left_top>
            <x_right_top>596</x_right_top>
            <y_right_top>136</y_right_top>
            <x_right_bottom>596</x_right_bottom>
            <y_right_bottom>149</y_right_bottom>
            <x_left_bottom>568</x_left_bottom>
            <y_left_bottom>149</y_left_bottom>
        </robndbox>
        <angle>0</angle>
    </object>
    <object>
        <type>robndbox</type>
        <name>ship</name>
        <pose>Unspecified</pose>
        <truncated>0</truncated>
        <difficult>0</difficult>
        <robndbox>
            <x_left_top>574</x_left_top>
            <y_left_top>155</y_left_top>
            <x_right_top>604</x_right_top>
            <y_right_top>155</y_right_top>
            <x_right_bottom>604</x_right_bottom>
            <y_right_bottom>167</y_right_bottom>
            <x_left_bottom>574</x_left_bottom>
            <y_left_bottom>167</y_left_bottom>
        </robndbox>
        <angle>0</angle>
    </object>
    <object>
        <type>robndbox</type>
        <name>ship</name>
        <pose>Unspecified</pose>
        <truncated>0</truncated>
        <difficult>0</difficult>
        <robndbox>
            <x_left_top>561</x_left_top>
            <y_left_top>208</y_left_top>
            <x_right_top>602</x_right_top>
            <y_right_top>208</y_right_top>
            <x_right_bottom>602</x_right_bottom>
            <y_right_bottom>225</y_right_bottom>
            <x_left_bottom>561</x_left_bottom>
            <y_left_bottom>225</y_left_bottom>
        </robndbox>
        <angle>0</angle>
    </object>
    <object>
        <type>robndbox</type>
        <name>ship</name>
        <pose>Unspecified</pose>
        <truncated>0</truncated>
        <difficult>0</difficult>
        <robndbox>
            <x_left_top>619</x_left_top>
            <y_left_top>89</y_left_top>
            <x_right_top>652</x_right_top>
            <y_right_top>89</y_right_top>
            <x_right_bottom>652</x_right_bottom>
            <y_right_bottom>101</y_right_bottom>
            <x_left_bottom>619</x_left_bottom>
            <y_left_bottom>101</y_left_bottom>
        </robndbox>
        <angle>0</angle>
    </object>
    <object>
        <type>robndbox</type>
        <name>ship</name>
        <pose>Unspecified</pose>
        <truncated>0</truncated>
        <difficult>0</difficult>
        <robndbox>
            <x_left_top>618</x_left_top>
            <y_left_top>119</y_left_top>
            <x_right_top>649</x_right_top>
            <y_right_top>119</y_right_top>
            <x_right_bottom>649</x_right_bottom>
            <y_right_bottom>131</y_right_bottom>
            <x_left_bottom>618</x_left_bottom>
            <y_left_bottom>131</y_left_bottom>
        </robndbox>
        <angle>0</angle>
    </object>
    <object>
        <type>robndbox</type>
        <name>ship</name>
        <pose>Unspecified</pose>
        <truncated>0</truncated>
        <difficult>0</difficult>
        <robndbox>
            <x_left_top>617</x_left_top>
            <y_left_top>131</y_left_top>
            <x_right_top>650</x_right_top>
            <y_right_top>131</y_right_top>
            <x_right_bottom>650</x_right_bottom>
            <y_right_bottom>143</y_right_bottom>
            <x_left_bottom>617</x_left_bottom>
            <y_left_bottom>143</y_left_bottom>
        </robndbox>
        <angle>0</angle>
    </object>
    <object>
        <type>robndbox</type>
        <name>ship</name>
        <pose>Unspecified</pose>
        <truncated>0</truncated>
        <difficult>0</difficult>
        <robndbox>
            <x_left_top>617</x_left_top>
            <y_left_top>149</y_left_top>
            <x_right_top>649</x_right_top>
            <y_right_top>149</y_right_top>
            <x_right_bottom>649</x_right_bottom>
            <y_right_bottom>161</y_right_bottom>
            <x_left_bottom>617</x_left_bottom>
            <y_left_bottom>161</y_left_bottom>
        </robndbox>
        <angle>0</angle>
    </object>
    <object>
        <type>robndbox</type>
        <name>ship</name>
        <pose>Unspecified</pose>
        <truncated>0</truncated>
        <difficult>0</difficult>
        <robndbox>
            <x_left_top>617</x_left_top>
            <y_left_top>162</y_left_top>
            <x_right_top>651</x_right_top>
            <y_right_top>162</y_right_top>
            <x_right_bottom>651</x_right_bottom>
            <y_right_bottom>173</y_right_bottom>
            <x_left_bottom>617</x_left_bottom>
            <y_left_bottom>173</y_left_bottom>
        </robndbox>
        <angle>0</angle>
    </object>
    <object>
        <type>robndbox</type>
        <name>ship</name>
        <pose>Unspecified</pose>
        <truncated>0</truncated>
        <difficult>0</difficult>
        <robndbox>
            <x_left_top>616</x_left_top>
            <y_left_top>179</y_left_top>
            <x_right_top>649</x_right_top>
            <y_right_top>179</y_right_top>
            <x_right_bottom>649</x_right_bottom>
            <y_right_bottom>192</y_right_bottom>
            <x_left_bottom>616</x_left_bottom>
            <y_left_bottom>192</y_left_bottom>
        </robndbox>
        <angle>0</angle>
    </object>
    <object>
        <type>robndbox</type>
        <name>ship</name>
        <pose>Unspecified</pose>
        <truncated>0</truncated>
        <difficult>0</difficult>
        <robndbox>
            <x_left_top>617</x_left_top>
            <y_left_top>192</y_left_top>
            <x_right_top>648</x_right_top>
            <y_right_top>192</y_right_top>
            <x_right_bottom>648</x_right_bottom>
            <y_right_bottom>205</y_right_bottom>
            <x_left_bottom>617</x_left_bottom>
            <y_left_bottom>205</y_left_bottom>
        </robndbox>
        <angle>0</angle>
    </object>
    <object>
        <type>robndbox</type>
        <name>ship</name>
        <pose>Unspecified</pose>
        <truncated>0</truncated>
        <difficult>0</difficult>
        <robndbox>
            <x_left_top>617</x_left_top>
            <y_left_top>210</y_left_top>
            <x_right_top>650</x_right_top>
            <y_right_top>210</y_right_top>
            <x_right_bottom>650</x_right_bottom>
            <y_right_bottom>223</y_right_bottom>
            <x_left_bottom>617</x_left_bottom>
            <y_left_bottom>223</y_left_bottom>
        </robndbox>
        <angle>0</angle>
    </object>
    <object>
        <type>robndbox</type>
        <name>ship</name>
        <pose>Unspecified</pose>
        <truncated>0</truncated>
        <difficult>0</difficult>
        <robndbox>
            <x_left_top>617</x_left_top>
            <y_left_top>223</y_left_top>
            <x_right_top>648</x_right_top>
            <y_right_top>223</y_right_top>
            <x_right_bottom>648</x_right_bottom>
            <y_right_bottom>235</y_right_bottom>
            <x_left_bottom>617</x_left_bottom>
            <y_left_bottom>235</y_left_bottom>
        </robndbox>
        <angle>0</angle>
    </object>
    <object>
        <type>robndbox</type>
        <name>ship</name>
        <pose>Unspecified</pose>
        <truncated>0</truncated>
        <difficult>0</difficult>
        <robndbox>
            <x_left_top>618</x_left_top>
            <y_left_top>242</y_left_top>
            <x_right_top>652</x_right_top>
            <y_right_top>242</y_right_top>
            <x_right_bottom>652</x_right_bottom>
            <y_right_bottom>255</y_right_bottom>
            <x_left_bottom>618</x_left_bottom>
            <y_left_bottom>255</y_left_bottom>
        </robndbox>
        <angle>0</angle>
    </object>
    <object>
        <type>robndbox</type>
        <name>ship</name>
        <pose>Unspecified</pose>
        <truncated>0</truncated>
        <difficult>0</difficult>
        <robndbox>
            <x_left_top>617</x_left_top>
            <y_left_top>255</y_left_top>
            <x_right_top>650</x_right_top>
            <y_right_top>255</y_right_top>
            <x_right_bottom>650</x_right_bottom>
            <y_right_bottom>270</y_right_bottom>
            <x_left_bottom>617</x_left_bottom>
            <y_left_bottom>270</y_left_bottom>
        </robndbox>
        <angle>0</angle>
    </object>
    <object>
        <type>robndbox</type>
        <name>ship</name>
        <pose>Unspecified</pose>
        <truncated>0</truncated>
        <difficult>0</difficult>
        <robndbox>
            <x_left_top>375</x_left_top>
            <y_left_top>138</y_left_top>
            <x_right_top>405</x_right_top>
            <y_right_top>140</y_right_top>
            <x_right_bottom>404</x_right_bottom>
            <y_right_bottom>152</y_right_bottom>
            <x_left_bottom>374</x_left_bottom>
            <y_left_bottom>150</y_left_bottom>
        </robndbox>
        <angle>4</angle>
    </object>
    <object>
        <type>robndbox</type>
        <name>ship</name>
        <pose>Unspecified</pose>
        <truncated>0</truncated>
        <difficult>0</difficult>
        <robndbox>
            <x_left_top>362</x_left_top>
            <y_left_top>158</y_left_top>
            <x_right_top>373</x_right_top>
            <y_right_top>159</y_right_top>
            <x_right_bottom>370</x_right_bottom>
            <y_right_bottom>194</y_right_bottom>
            <x_left_bottom>359</x_left_bottom>
            <y_left_bottom>193</y_left_bottom>
        </robndbox>
        <angle>5</angle>
    </object>
    <object>
        <type>robndbox</type>
        <name>harbor</name>
        <pose>Unspecified</pose>
        <truncated>0</truncated>
        <difficult>0</difficult>
        <robndbox>
            <x_left_top>369</x_left_top>
            <y_left_top>25</y_left_top>
            <x_right_top>495</x_right_top>
            <y_right_top>34</y_right_top>
            <x_right_bottom>485</x_right_bottom>
            <y_right_bottom>165</y_right_bottom>
            <x_left_bottom>359</x_left_bottom>
            <y_left_bottom>156</y_left_bottom>
        </robndbox>
        <angle>4</angle>
    </object>
    <object>
        <type>robndbox</type>
        <name>ship</name>
        <pose>Unspecified</pose>
        <truncated>0</truncated>
        <difficult>0</difficult>
        <robndbox>
            <x_left_top>291</x_left_top>
            <y_left_top>134</y_left_top>
            <x_right_top>322</x_right_top>
            <y_right_top>147</y_right_top>
            <x_right_bottom>317</x_right_bottom>
            <y_right_bottom>158</y_right_bottom>
            <x_left_bottom>286</x_left_bottom>
            <y_left_bottom>145</y_left_bottom>
        </robndbox>
        <angle>24</angle>
    </object>
    <object>
        <type>robndbox</type>
        <name>ship</name>
        <pose>Unspecified</pose>
        <truncated>0</truncated>
        <difficult>0</difficult>
        <robndbox>
            <x_left_top>263</x_left_top>
            <y_left_top>124</y_left_top>
            <x_right_top>276</x_right_top>
            <y_right_top>124</y_right_top>
            <x_right_bottom>276</x_right_bottom>
            <y_right_bottom>162</y_right_bottom>
            <x_left_bottom>263</x_left_bottom>
            <y_left_bottom>163</y_left_bottom>
        </robndbox>
        <angle>-0.2</angle>
    </object>
    <object>
        <type>robndbox</type>
        <name>harbor</name>
        <pose>Unspecified</pose>
        <truncated>0</truncated>
        <difficult>0</difficult>
        <robndbox>
            <x_left_top>166</x_left_top>
            <y_left_top>110</y_left_top>
            <x_right_top>241</x_right_top>
            <y_right_top>113</y_right_top>
            <x_right_bottom>238</x_right_bottom>
            <y_right_bottom>158</y_right_bottom>
            <x_left_bottom>164</x_left_bottom>
            <y_left_bottom>154</y_left_bottom>
        </robndbox>
        <angle>2.6</angle>
    </object>
    <object>
        <type>robndbox</type>
        <name>ship</name>
        <pose>Unspecified</pose>
        <truncated>0</truncated>
        <difficult>0</difficult>
        <robndbox>
            <x_left_top>96</x_left_top>
            <y_left_top>228</y_left_top>
            <x_right_top>114</x_right_top>
            <y_right_top>234</y_right_top>
            <x_right_bottom>91</x_right_bottom>
            <y_right_bottom>296</y_right_bottom>
            <x_left_bottom>73</x_left_bottom>
            <y_left_bottom>289</y_left_bottom>
        </robndbox>
        <angle>20.4</angle>
    </object>
    <object>
        <type>robndbox</type>
        <name>ship</name>
        <pose>Unspecified</pose>
        <truncated>0</truncated>
        <difficult>0</difficult>
        <robndbox>
            <x_left_top>61</x_left_top>
            <y_left_top>204</y_left_top>
            <x_right_top>74</x_right_top>
            <y_right_top>209</y_right_top>
            <x_right_bottom>58</x_right_bottom>
            <y_right_bottom>253</y_right_bottom>
            <x_left_bottom>44</x_left_bottom>
            <y_left_bottom>248</y_left_bottom>
        </robndbox>
        <angle>20.4</angle>
    </object>
    <object>
        <type>robndbox</type>
        <name>ship</name>
        <pose>Unspecified</pose>
        <truncated>0</truncated>
        <difficult>0</difficult>
        <robndbox>
            <x_left_top>70</x_left_top>
            <y_left_top>181</y_left_top>
            <x_right_top>108</x_right_top>
            <y_right_top>195</y_right_top>
            <x_right_bottom>103</x_right_bottom>
            <y_right_bottom>211</y_right_bottom>
            <x_left_bottom>65</x_left_bottom>
            <y_left_bottom>197</y_left_bottom>
        </robndbox>
        <angle>20.4</angle>
    </object>
    <object>
        <type>robndbox</type>
        <name>harbor</name>
        <pose>Unspecified</pose>
        <truncated>0</truncated>
        <difficult>0</difficult>
        <robndbox>
            <x_left_top>80</x_left_top>
            <y_left_top>86</y_left_top>
            <x_right_top>149</x_right_top>
            <y_right_top>106</y_right_top>
            <x_right_bottom>113</x_right_bottom>
            <y_right_bottom>229</y_right_bottom>
            <x_left_bottom>44</x_left_bottom>
            <y_left_bottom>209</y_left_bottom>
        </robndbox>
        <angle>16.6</angle>
    </object>
    <object>
        <type>robndbox</type>
        <name>ship</name>
        <pose>Unspecified</pose>
        <truncated>0</truncated>
        <difficult>0</difficult>
        <robndbox>
            <x_left_top>44</x_left_top>
            <y_left_top>193</y_left_top>
            <x_right_top>58</x_right_top>
            <y_right_top>201</y_right_top>
            <x_right_bottom>29</x_right_bottom>
            <y_right_bottom>256</y_right_bottom>
            <x_left_bottom>15</x_left_bottom>
            <y_left_bottom>249</y_left_bottom>
        </robndbox>
        <angle>27.6</angle>
    </object>
</annotation>
