<?xml version="1.0" encoding="UTF-8"?>
<annotation>
    <folder>/JPEGImages-trainval.zip/JPEGImages-trainval/JPEGImages-trainval</folder>
    <filename>07195.jpg</filename>
    <path>/JPEGImages-trainval.zip/JPEGImages-trainval/JPEGImages-trainval</path>
    <source>
        <database>Unknown</database>
    </source>
    <size>
        <width>800</width>
        <height>800</height>
        <depth>3</depth>
    </size>
    <segmented>0</segmented>
    <object>
        <type>robndbox</type>
        <name>ship</name>
        <pose>Unspecified</pose>
        <truncated>0</truncated>
        <difficult>0</difficult>
        <robndbox>
            <x_left_top>435</x_left_top>
            <y_left_top>511</y_left_top>
            <x_right_top>476</x_right_top>
            <y_right_top>511</y_right_top>
            <x_right_bottom>476</x_right_bottom>
            <y_right_bottom>655</y_right_bottom>
            <x_left_bottom>435</x_left_bottom>
            <y_left_bottom>655</y_left_bottom>
        </robndbox>
        <angle>0</angle>
    </object>
    <object>
        <type>robndbox</type>
        <name>ship</name>
        <pose>Unspecified</pose>
        <truncated>0</truncated>
        <difficult>0</difficult>
        <robndbox>
            <x_left_top>52</x_left_top>
            <y_left_top>660</y_left_top>
            <x_right_top>129</x_right_top>
            <y_right_top>658</y_right_top>
            <x_right_bottom>129</x_right_bottom>
            <y_right_bottom>685</y_right_bottom>
            <x_left_bottom>52</x_left_bottom>
            <y_left_bottom>687</y_left_bottom>
        </robndbox>
        <angle>-1.4</angle>
    </object>
    <object>
        <type>robndbox</type>
        <name>ship</name>
        <pose>Unspecified</pose>
        <truncated>0</truncated>
        <difficult>0</difficult>
        <robndbox>
            <x_left_top>304</x_left_top>
            <y_left_top>527</y_left_top>
            <x_right_top>345</x_right_top>
            <y_right_top>534</y_right_top>
            <x_right_bottom>326</x_right_bottom>
            <y_right_bottom>641</y_right_bottom>
            <x_left_bottom>285</x_left_bottom>
            <y_left_bottom>634</y_left_bottom>
        </robndbox>
        <angle>10</angle>
    </object>
    <object>
        <type>robndbox</type>
        <name>ship</name>
        <pose>Unspecified</pose>
        <truncated>0</truncated>
        <difficult>0</difficult>
        <robndbox>
            <x_left_top>389</x_left_top>
            <y_left_top>537</y_left_top>
            <x_right_top>430</x_right_top>
            <y_right_top>540</y_right_top>
            <x_right_bottom>424</x_right_bottom>
            <y_right_bottom>635</y_right_bottom>
            <x_left_bottom>382</x_left_bottom>
            <y_left_bottom>632</y_left_bottom>
        </robndbox>
        <angle>4</angle>
    </object>
    <object>
        <type>robndbox</type>
        <name>ship</name>
        <pose>Unspecified</pose>
        <truncated>0</truncated>
        <difficult>0</difficult>
        <robndbox>
            <x_left_top>363</x_left_top>
            <y_left_top>664</y_left_top>
            <x_right_top>440</x_right_top>
            <y_right_top>669</y_right_top>
            <x_right_bottom>438</x_right_bottom>
            <y_right_bottom>697</y_right_bottom>
            <x_left_bottom>361</x_left_bottom>
            <y_left_bottom>691</y_left_bottom>
        </robndbox>
        <angle>4</angle>
    </object>
    <object>
        <type>robndbox</type>
        <name>ship</name>
        <pose>Unspecified</pose>
        <truncated>0</truncated>
        <difficult>0</difficult>
        <robndbox>
            <x_left_top>378</x_left_top>
            <y_left_top>715</y_left_top>
            <x_right_top>460</x_right_top>
            <y_right_top>724</y_right_top>
            <x_right_bottom>456</x_right_bottom>
            <y_right_bottom>764</y_right_bottom>
            <x_left_bottom>374</x_left_bottom>
            <y_left_bottom>755</y_left_bottom>
        </robndbox>
        <angle>6</angle>
    </object>
    <object>
        <type>robndbox</type>
        <name>ship</name>
        <pose>Unspecified</pose>
        <truncated>0</truncated>
        <difficult>0</difficult>
        <robndbox>
            <x_left_top>569</x_left_top>
            <y_left_top>665</y_left_top>
            <x_right_top>593</x_right_top>
            <y_right_top>660</y_right_top>
            <x_right_bottom>609</x_right_bottom>
            <y_right_bottom>736</y_right_bottom>
            <x_left_bottom>584</x_left_bottom>
            <y_left_bottom>741</y_left_bottom>
        </robndbox>
        <angle>-11.8</angle>
    </object>
    <object>
        <type>robndbox</type>
        <name>ship</name>
        <pose>Unspecified</pose>
        <truncated>0</truncated>
        <difficult>0</difficult>
        <robndbox>
            <x_left_top>601</x_left_top>
            <y_left_top>683</y_left_top>
            <x_right_top>669</x_right_top>
            <y_right_top>690</y_right_top>
            <x_right_bottom>666</x_right_bottom>
            <y_right_bottom>713</y_right_bottom>
            <x_left_bottom>599</x_left_bottom>
            <y_left_bottom>706</y_left_bottom>
        </robndbox>
        <angle>6</angle>
    </object>
    <object>
        <type>robndbox</type>
        <name>ship</name>
        <pose>Unspecified</pose>
        <truncated>0</truncated>
        <difficult>0</difficult>
        <robndbox>
            <x_left_top>595</x_left_top>
            <y_left_top>659</y_left_top>
            <x_right_top>667</x_right_top>
            <y_right_top>667</y_right_top>
            <x_right_bottom>665</x_right_bottom>
            <y_right_bottom>690</y_right_bottom>
            <x_left_bottom>593</x_left_bottom>
            <y_left_bottom>683</y_left_bottom>
        </robndbox>
        <angle>6</angle>
    </object>
    <object>
        <type>robndbox</type>
        <name>ship</name>
        <pose>Unspecified</pose>
        <truncated>0</truncated>
        <difficult>0</difficult>
        <robndbox>
            <x_left_top>578</x_left_top>
            <y_left_top>525</y_left_top>
            <x_right_top>620</x_right_top>
            <y_right_top>527</y_right_top>
            <x_right_bottom>615</x_right_bottom>
            <y_right_bottom>627</y_right_bottom>
            <x_left_bottom>573</x_left_bottom>
            <y_left_bottom>625</y_left_bottom>
        </robndbox>
        <angle>3</angle>
    </object>
    <object>
        <type>robndbox</type>
        <name>harbor</name>
        <pose>Unspecified</pose>
        <truncated>0</truncated>
        <difficult>0</difficult>
        <robndbox>
            <x_left_top>46</x_left_top>
            <y_left_top>511</y_left_top>
            <x_right_top>787</x_right_top>
            <y_right_top>550</y_right_top>
            <x_right_bottom>772</x_right_bottom>
            <y_right_bottom>824</y_right_bottom>
            <x_left_bottom>32</x_left_bottom>
            <y_left_bottom>785</y_left_bottom>
        </robndbox>
        <angle>3</angle>
    </object>
</annotation>
