<?xml version="1.0" encoding="UTF-8"?>
<annotation>
    <folder>/JPEGImages-test.zip/JPEGImages-test/JPEGImages-test</folder>
    <filename>14201.jpg</filename>
    <path>/JPEGImages-test.zip/JPEGImages-test/JPEGImages-test</path>
    <source>
        <database>Unknown</database>
    </source>
    <size>
        <width>800</width>
        <height>800</height>
        <depth>3</depth>
    </size>
    <segmented>0</segmented>
    <object>
        <type>robndbox</type>
        <name>airplane</name>
        <pose>Unspecified</pose>
        <truncated>0</truncated>
        <difficult>0</difficult>
        <robndbox>
            <x_left_top>81</x_left_top>
            <y_left_top>33</y_left_top>
            <x_right_top>174</x_right_top>
            <y_right_top>33</y_right_top>
            <x_right_bottom>174</x_right_bottom>
            <y_right_bottom>107</y_right_bottom>
            <x_left_bottom>81</x_left_bottom>
            <y_left_bottom>107</y_left_bottom>
        </robndbox>
        <angle>0</angle>
    </object>
    <object>
        <type>robndbox</type>
        <name>airplane</name>
        <pose>Unspecified</pose>
        <truncated>0</truncated>
        <difficult>0</difficult>
        <robndbox>
            <x_left_top>81</x_left_top>
            <y_left_top>146</y_left_top>
            <x_right_top>176</x_right_top>
            <y_right_top>146</y_right_top>
            <x_right_bottom>176</x_right_bottom>
            <y_right_bottom>231</y_right_bottom>
            <x_left_bottom>81</x_left_bottom>
            <y_left_bottom>231</y_left_bottom>
        </robndbox>
        <angle>0</angle>
    </object>
    <object>
        <type>robndbox</type>
        <name>airplane</name>
        <pose>Unspecified</pose>
        <truncated>0</truncated>
        <difficult>0</difficult>
        <robndbox>
            <x_left_top>104</x_left_top>
            <y_left_top>251</y_left_top>
            <x_right_top>181</x_right_top>
            <y_right_top>251</y_right_top>
            <x_right_bottom>181</x_right_bottom>
            <y_right_bottom>321</y_right_bottom>
            <x_left_bottom>104</x_left_bottom>
            <y_left_bottom>321</y_left_bottom>
        </robndbox>
        <angle>0</angle>
    </object>
    <object>
        <type>robndbox</type>
        <name>airplane</name>
        <pose>Unspecified</pose>
        <truncated>0</truncated>
        <difficult>0</difficult>
        <robndbox>
            <x_left_top>97</x_left_top>
            <y_left_top>296</y_left_top>
            <x_right_top>153</x_right_top>
            <y_right_top>296</y_right_top>
            <x_right_bottom>153</x_right_bottom>
            <y_right_bottom>355</y_right_bottom>
            <x_left_bottom>97</x_left_bottom>
            <y_left_bottom>355</y_left_bottom>
        </robndbox>
        <angle>0</angle>
    </object>
    <object>
        <type>robndbox</type>
        <name>airplane</name>
        <pose>Unspecified</pose>
        <truncated>0</truncated>
        <difficult>0</difficult>
        <robndbox>
            <x_left_top>103</x_left_top>
            <y_left_top>372</y_left_top>
            <x_right_top>165</x_right_top>
            <y_right_top>372</y_right_top>
            <x_right_bottom>165</x_right_bottom>
            <y_right_bottom>423</y_right_bottom>
            <x_left_bottom>103</x_left_bottom>
            <y_left_bottom>423</y_left_bottom>
        </robndbox>
        <angle>0</angle>
    </object>
    <object>
        <type>robndbox</type>
        <name>airplane</name>
        <pose>Unspecified</pose>
        <truncated>0</truncated>
        <difficult>0</difficult>
        <robndbox>
            <x_left_top>96</x_left_top>
            <y_left_top>437</y_left_top>
            <x_right_top>217</x_right_top>
            <y_right_top>437</y_right_top>
            <x_right_bottom>217</x_right_bottom>
            <y_right_bottom>609</y_right_bottom>
            <x_left_bottom>96</x_left_bottom>
            <y_left_bottom>609</y_left_bottom>
        </robndbox>
        <angle>0</angle>
    </object>
    <object>
        <type>robndbox</type>
        <name>airplane</name>
        <pose>Unspecified</pose>
        <truncated>0</truncated>
        <difficult>0</difficult>
        <robndbox>
            <x_left_top>203</x_left_top>
            <y_left_top>497</y_left_top>
            <x_right_top>254</x_right_top>
            <y_right_top>497</y_right_top>
            <x_right_bottom>254</x_right_bottom>
            <y_right_bottom>546</y_right_bottom>
            <x_left_bottom>203</x_left_bottom>
            <y_left_bottom>546</y_left_bottom>
        </robndbox>
        <angle>0</angle>
    </object>
    <object>
        <type>robndbox</type>
        <name>airplane</name>
        <pose>Unspecified</pose>
        <truncated>0</truncated>
        <difficult>0</difficult>
        <robndbox>
            <x_left_top>218</x_left_top>
            <y_left_top>550</y_left_top>
            <x_right_top>291</x_right_top>
            <y_right_top>550</y_right_top>
            <x_right_bottom>291</x_right_bottom>
            <y_right_bottom>630</y_right_bottom>
            <x_left_bottom>218</x_left_bottom>
            <y_left_bottom>630</y_left_bottom>
        </robndbox>
        <angle>0</angle>
    </object>
    <object>
        <type>robndbox</type>
        <name>airplane</name>
        <pose>Unspecified</pose>
        <truncated>0</truncated>
        <difficult>0</difficult>
        <robndbox>
            <x_left_top>312</x_left_top>
            <y_left_top>545</y_left_top>
            <x_right_top>385</x_right_top>
            <y_right_top>545</y_right_top>
            <x_right_bottom>385</x_right_bottom>
            <y_right_bottom>626</y_right_bottom>
            <x_left_bottom>312</x_left_bottom>
            <y_left_bottom>626</y_left_bottom>
        </robndbox>
        <angle>0</angle>
    </object>
    <object>
        <type>robndbox</type>
        <name>airplane</name>
        <pose>Unspecified</pose>
        <truncated>0</truncated>
        <difficult>0</difficult>
        <robndbox>
            <x_left_top>349</x_left_top>
            <y_left_top>98</y_left_top>
            <x_right_top>436</x_right_top>
            <y_right_top>98</y_right_top>
            <x_right_bottom>436</x_right_bottom>
            <y_right_bottom>196</y_right_bottom>
            <x_left_bottom>349</x_left_bottom>
            <y_left_bottom>196</y_left_bottom>
        </robndbox>
        <angle>0</angle>
    </object>
    <object>
        <type>robndbox</type>
        <name>airplane</name>
        <pose>Unspecified</pose>
        <truncated>0</truncated>
        <difficult>0</difficult>
        <robndbox>
            <x_left_top>701</x_left_top>
            <y_left_top>202</y_left_top>
            <x_right_top>751</x_right_top>
            <y_right_top>202</y_right_top>
            <x_right_bottom>751</x_right_bottom>
            <y_right_bottom>264</y_right_bottom>
            <x_left_bottom>701</x_left_bottom>
            <y_left_bottom>264</y_left_bottom>
        </robndbox>
        <angle>0</angle>
    </object>
    <object>
        <type>robndbox</type>
        <name>airplane</name>
        <pose>Unspecified</pose>
        <truncated>0</truncated>
        <difficult>0</difficult>
        <robndbox>
            <x_left_top>335</x_left_top>
            <y_left_top>432</y_left_top>
            <x_right_top>371</x_right_top>
            <y_right_top>432</y_right_top>
            <x_right_bottom>371</x_right_bottom>
            <y_right_bottom>475</y_right_bottom>
            <x_left_bottom>335</x_left_bottom>
            <y_left_bottom>475</y_left_bottom>
        </robndbox>
        <angle>0</angle>
    </object>
    <object>
        <type>robndbox</type>
        <name>airplane</name>
        <pose>Unspecified</pose>
        <truncated>0</truncated>
        <difficult>0</difficult>
        <robndbox>
            <x_left_top>417</x_left_top>
            <y_left_top>433</y_left_top>
            <x_right_top>445</x_right_top>
            <y_right_top>433</y_right_top>
            <x_right_bottom>445</x_right_bottom>
            <y_right_bottom>474</y_right_bottom>
            <x_left_bottom>417</x_left_bottom>
            <y_left_bottom>474</y_left_bottom>
        </robndbox>
        <angle>0</angle>
    </object>
    <object>
        <type>robndbox</type>
        <name>airplane</name>
        <pose>Unspecified</pose>
        <truncated>0</truncated>
        <difficult>0</difficult>
        <robndbox>
            <x_left_top>417</x_left_top>
            <y_left_top>506</y_left_top>
            <x_right_top>447</x_right_top>
            <y_right_top>506</y_right_top>
            <x_right_bottom>447</x_right_bottom>
            <y_right_bottom>544</y_right_bottom>
            <x_left_bottom>417</x_left_bottom>
            <y_left_bottom>544</y_left_bottom>
        </robndbox>
        <angle>0</angle>
    </object>
    <object>
        <type>robndbox</type>
        <name>airplane</name>
        <pose>Unspecified</pose>
        <truncated>0</truncated>
        <difficult>0</difficult>
        <robndbox>
            <x_left_top>429</x_left_top>
            <y_left_top>533</y_left_top>
            <x_right_top>478</x_right_top>
            <y_right_top>533</y_right_top>
            <x_right_bottom>478</x_right_bottom>
            <y_right_bottom>597</y_right_bottom>
            <x_left_bottom>429</x_left_bottom>
            <y_left_bottom>597</y_left_bottom>
        </robndbox>
        <angle>0</angle>
    </object>
    <object>
        <type>robndbox</type>
        <name>airplane</name>
        <pose>Unspecified</pose>
        <truncated>0</truncated>
        <difficult>0</difficult>
        <robndbox>
            <x_left_top>401</x_left_top>
            <y_left_top>304</y_left_top>
            <x_right_top>435</x_right_top>
            <y_right_top>304</y_right_top>
            <x_right_bottom>435</x_right_bottom>
            <y_right_bottom>344</y_right_bottom>
            <x_left_bottom>401</x_left_bottom>
            <y_left_bottom>344</y_left_bottom>
        </robndbox>
        <angle>0</angle>
    </object>
    <object>
        <type>robndbox</type>
        <name>airplane</name>
        <pose>Unspecified</pose>
        <truncated>0</truncated>
        <difficult>0</difficult>
        <robndbox>
            <x_left_top>405</x_left_top>
            <y_left_top>346</y_left_top>
            <x_right_top>435</x_right_top>
            <y_right_top>346</y_right_top>
            <x_right_bottom>435</x_right_bottom>
            <y_right_bottom>386</y_right_bottom>
            <x_left_bottom>405</x_left_bottom>
            <y_left_bottom>386</y_left_bottom>
        </robndbox>
        <angle>0</angle>
    </object>
    <object>
        <type>robndbox</type>
        <name>vehicle</name>
        <pose>Unspecified</pose>
        <truncated>0</truncated>
        <difficult>0</difficult>
        <robndbox>
            <x_left_top>430</x_left_top>
            <y_left_top>268</y_left_top>
            <x_right_top>437</x_right_top>
            <y_right_top>268</y_right_top>
            <x_right_bottom>437</x_right_bottom>
            <y_right_bottom>287</y_right_bottom>
            <x_left_bottom>430</x_left_bottom>
            <y_left_bottom>287</y_left_bottom>
        </robndbox>
        <angle>0</angle>
    </object>
    <object>
        <type>robndbox</type>
        <name>vehicle</name>
        <pose>Unspecified</pose>
        <truncated>0</truncated>
        <difficult>0</difficult>
        <robndbox>
            <x_left_top>385</x_left_top>
            <y_left_top>269</y_left_top>
            <x_right_top>395</x_right_top>
            <y_right_top>269</y_right_top>
            <x_right_bottom>395</x_right_bottom>
            <y_right_bottom>288</y_right_bottom>
            <x_left_bottom>385</x_left_bottom>
            <y_left_bottom>288</y_left_bottom>
        </robndbox>
        <angle>0</angle>
    </object>
    <object>
        <type>robndbox</type>
        <name>vehicle</name>
        <pose>Unspecified</pose>
        <truncated>0</truncated>
        <difficult>0</difficult>
        <robndbox>
            <x_left_top>420</x_left_top>
            <y_left_top>270</y_left_top>
            <x_right_top>428</x_right_top>
            <y_right_top>270</y_right_top>
            <x_right_bottom>428</x_right_bottom>
            <y_right_bottom>288</y_right_bottom>
            <x_left_bottom>420</x_left_bottom>
            <y_left_bottom>288</y_left_bottom>
        </robndbox>
        <angle>0</angle>
    </object>
    <object>
        <type>robndbox</type>
        <name>vehicle</name>
        <pose>Unspecified</pose>
        <truncated>0</truncated>
        <difficult>0</difficult>
        <robndbox>
            <x_left_top>397</x_left_top>
            <y_left_top>269</y_left_top>
            <x_right_top>406</x_right_top>
            <y_right_top>269</y_right_top>
            <x_right_bottom>406</x_right_bottom>
            <y_right_bottom>288</y_right_bottom>
            <x_left_bottom>397</x_left_bottom>
            <y_left_bottom>288</y_left_bottom>
        </robndbox>
        <angle>0</angle>
    </object>
    <object>
        <type>robndbox</type>
        <name>vehicle</name>
        <pose>Unspecified</pose>
        <truncated>0</truncated>
        <difficult>0</difficult>
        <robndbox>
            <x_left_top>648</x_left_top>
            <y_left_top>259</y_left_top>
            <x_right_top>664</x_right_top>
            <y_right_top>259</y_right_top>
            <x_right_bottom>664</x_right_bottom>
            <y_right_bottom>266</y_right_bottom>
            <x_left_bottom>648</x_left_bottom>
            <y_left_bottom>266</y_left_bottom>
        </robndbox>
        <angle>0</angle>
    </object>
    <object>
        <type>robndbox</type>
        <name>vehicle</name>
        <pose>Unspecified</pose>
        <truncated>0</truncated>
        <difficult>0</difficult>
        <robndbox>
            <x_left_top>768</x_left_top>
            <y_left_top>209</y_left_top>
            <x_right_top>785</x_right_top>
            <y_right_top>209</y_right_top>
            <x_right_bottom>785</x_right_bottom>
            <y_right_bottom>217</y_right_bottom>
            <x_left_bottom>768</x_left_bottom>
            <y_left_bottom>217</y_left_bottom>
        </robndbox>
        <angle>0</angle>
    </object>
    <object>
        <type>robndbox</type>
        <name>vehicle</name>
        <pose>Unspecified</pose>
        <truncated>0</truncated>
        <difficult>0</difficult>
        <robndbox>
            <x_left_top>768</x_left_top>
            <y_left_top>219</y_left_top>
            <x_right_top>784</x_right_top>
            <y_right_top>219</y_right_top>
            <x_right_bottom>784</x_right_bottom>
            <y_right_bottom>226</y_right_bottom>
            <x_left_bottom>768</x_left_bottom>
            <y_left_bottom>226</y_left_bottom>
        </robndbox>
        <angle>0</angle>
    </object>
    <object>
        <type>robndbox</type>
        <name>vehicle</name>
        <pose>Unspecified</pose>
        <truncated>0</truncated>
        <difficult>0</difficult>
        <robndbox>
            <x_left_top>766</x_left_top>
            <y_left_top>229</y_left_top>
            <x_right_top>783</x_right_top>
            <y_right_top>229</y_right_top>
            <x_right_bottom>783</x_right_bottom>
            <y_right_bottom>235</y_right_bottom>
            <x_left_bottom>766</x_left_bottom>
            <y_left_bottom>235</y_left_bottom>
        </robndbox>
        <angle>0</angle>
    </object>
    <object>
        <type>robndbox</type>
        <name>vehicle</name>
        <pose>Unspecified</pose>
        <truncated>0</truncated>
        <difficult>0</difficult>
        <robndbox>
            <x_left_top>765</x_left_top>
            <y_left_top>238</y_left_top>
            <x_right_top>782</x_right_top>
            <y_right_top>238</y_right_top>
            <x_right_bottom>782</x_right_bottom>
            <y_right_bottom>246</y_right_bottom>
            <x_left_bottom>765</x_left_bottom>
            <y_left_bottom>246</y_left_bottom>
        </robndbox>
        <angle>0</angle>
    </object>
    <object>
        <type>robndbox</type>
        <name>vehicle</name>
        <pose>Unspecified</pose>
        <truncated>0</truncated>
        <difficult>0</difficult>
        <robndbox>
            <x_left_top>767</x_left_top>
            <y_left_top>251</y_left_top>
            <x_right_top>783</x_right_top>
            <y_right_top>251</y_right_top>
            <x_right_bottom>783</x_right_bottom>
            <y_right_bottom>257</y_right_bottom>
            <x_left_bottom>767</x_left_bottom>
            <y_left_bottom>257</y_left_bottom>
        </robndbox>
        <angle>0</angle>
    </object>
    <object>
        <type>robndbox</type>
        <name>vehicle</name>
        <pose>Unspecified</pose>
        <truncated>0</truncated>
        <difficult>0</difficult>
        <robndbox>
            <x_left_top>687</x_left_top>
            <y_left_top>22</y_left_top>
            <x_right_top>706</x_right_top>
            <y_right_top>22</y_right_top>
            <x_right_bottom>706</x_right_bottom>
            <y_right_bottom>30</y_right_bottom>
            <x_left_bottom>687</x_left_bottom>
            <y_left_bottom>30</y_left_bottom>
        </robndbox>
        <angle>0</angle>
    </object>
    <object>
        <type>robndbox</type>
        <name>vehicle</name>
        <pose>Unspecified</pose>
        <truncated>0</truncated>
        <difficult>0</difficult>
        <robndbox>
            <x_left_top>687</x_left_top>
            <y_left_top>43</y_left_top>
            <x_right_top>706</x_right_top>
            <y_right_top>43</y_right_top>
            <x_right_bottom>706</x_right_bottom>
            <y_right_bottom>50</y_right_bottom>
            <x_left_bottom>687</x_left_bottom>
            <y_left_bottom>50</y_left_bottom>
        </robndbox>
        <angle>0</angle>
    </object>
    <object>
        <type>robndbox</type>
        <name>vehicle</name>
        <pose>Unspecified</pose>
        <truncated>0</truncated>
        <difficult>0</difficult>
        <robndbox>
            <x_left_top>737</x_left_top>
            <y_left_top>11</y_left_top>
            <x_right_top>755</x_right_top>
            <y_right_top>11</y_right_top>
            <x_right_bottom>755</x_right_bottom>
            <y_right_bottom>19</y_right_bottom>
            <x_left_bottom>737</x_left_bottom>
            <y_left_bottom>19</y_left_bottom>
        </robndbox>
        <angle>0</angle>
    </object>
    <object>
        <type>robndbox</type>
        <name>vehicle</name>
        <pose>Unspecified</pose>
        <truncated>0</truncated>
        <difficult>0</difficult>
        <robndbox>
            <x_left_top>733</x_left_top>
            <y_left_top>32</y_left_top>
            <x_right_top>754</x_right_top>
            <y_right_top>32</y_right_top>
            <x_right_bottom>754</x_right_bottom>
            <y_right_bottom>39</y_right_bottom>
            <x_left_bottom>733</x_left_bottom>
            <y_left_bottom>39</y_left_bottom>
        </robndbox>
        <angle>0</angle>
    </object>
    <object>
        <type>robndbox</type>
        <name>vehicle</name>
        <pose>Unspecified</pose>
        <truncated>0</truncated>
        <difficult>0</difficult>
        <robndbox>
            <x_left_top>731</x_left_top>
            <y_left_top>43</y_left_top>
            <x_right_top>749</x_right_top>
            <y_right_top>43</y_right_top>
            <x_right_bottom>749</x_right_bottom>
            <y_right_bottom>50</y_right_bottom>
            <x_left_bottom>731</x_left_bottom>
            <y_left_bottom>50</y_left_bottom>
        </robndbox>
        <angle>0</angle>
    </object>
    <object>
        <type>robndbox</type>
        <name>vehicle</name>
        <pose>Unspecified</pose>
        <truncated>0</truncated>
        <difficult>0</difficult>
        <robndbox>
            <x_left_top>736</x_left_top>
            <y_left_top>62</y_left_top>
            <x_right_top>754</x_right_top>
            <y_right_top>62</y_right_top>
            <x_right_bottom>754</x_right_bottom>
            <y_right_bottom>70</y_right_bottom>
            <x_left_bottom>736</x_left_bottom>
            <y_left_bottom>70</y_left_bottom>
        </robndbox>
        <angle>0</angle>
    </object>
    <object>
        <type>robndbox</type>
        <name>vehicle</name>
        <pose>Unspecified</pose>
        <truncated>0</truncated>
        <difficult>0</difficult>
        <robndbox>
            <x_left_top>736</x_left_top>
            <y_left_top>86</y_left_top>
            <x_right_top>757</x_right_top>
            <y_right_top>86</y_right_top>
            <x_right_bottom>757</x_right_bottom>
            <y_right_bottom>92</y_right_bottom>
            <x_left_bottom>736</x_left_bottom>
            <y_left_bottom>92</y_left_bottom>
        </robndbox>
        <angle>0</angle>
    </object>
    <object>
        <type>robndbox</type>
        <name>airplane</name>
        <pose>Unspecified</pose>
        <truncated>0</truncated>
        <difficult>0</difficult>
        <robndbox>
            <x_left_top>203</x_left_top>
            <y_left_top>418</y_left_top>
            <x_right_top>249</x_right_top>
            <y_right_top>464</y_right_top>
            <x_right_bottom>196</x_right_bottom>
            <y_right_bottom>517</y_right_bottom>
            <x_left_bottom>150</x_left_bottom>
            <y_left_bottom>472</y_left_bottom>
        </robndbox>
        <angle>44.8</angle>
    </object>
    <object>
        <type>robndbox</type>
        <name>airplane</name>
        <pose>Unspecified</pose>
        <truncated>0</truncated>
        <difficult>0</difficult>
        <robndbox>
            <x_left_top>155</x_left_top>
            <y_left_top>547</y_left_top>
            <x_right_top>200</x_right_top>
            <y_right_top>532</y_right_top>
            <x_right_bottom>221</x_right_bottom>
            <y_right_bottom>594</y_right_bottom>
            <x_left_bottom>176</x_left_bottom>
            <y_left_bottom>609</y_left_bottom>
        </robndbox>
        <angle>-18.4</angle>
    </object>
    <object>
        <type>robndbox</type>
        <name>airplane</name>
        <pose>Unspecified</pose>
        <truncated>0</truncated>
        <difficult>0</difficult>
        <robndbox>
            <x_left_top>383</x_left_top>
            <y_left_top>495</y_left_top>
            <x_right_top>435</x_right_top>
            <y_right_top>524</y_right_top>
            <x_right_bottom>411</x_right_bottom>
            <y_right_bottom>567</y_right_bottom>
            <x_left_bottom>359</x_left_bottom>
            <y_left_bottom>538</y_left_bottom>
        </robndbox>
        <angle>29</angle>
    </object>
    <object>
        <type>robndbox</type>
        <name>airplane</name>
        <pose>Unspecified</pose>
        <truncated>0</truncated>
        <difficult>0</difficult>
        <robndbox>
            <x_left_top>452</x_left_top>
            <y_left_top>534</y_left_top>
            <x_right_top>499</x_right_top>
            <y_right_top>514</y_right_top>
            <x_right_bottom>518</x_right_bottom>
            <y_right_bottom>559</y_right_bottom>
            <x_left_bottom>471</x_left_bottom>
            <y_left_bottom>578</y_left_bottom>
        </robndbox>
        <angle>-23</angle>
    </object>
    <object>
        <type>robndbox</type>
        <name>airplane</name>
        <pose>Unspecified</pose>
        <truncated>0</truncated>
        <difficult>0</difficult>
        <robndbox>
            <x_left_top>444</x_left_top>
            <y_left_top>127</y_left_top>
            <x_right_top>478</x_right_top>
            <y_right_top>121</y_right_top>
            <x_right_bottom>485</x_right_bottom>
            <y_right_bottom>156</y_right_bottom>
            <x_left_bottom>451</x_left_bottom>
            <y_left_bottom>163</y_left_bottom>
        </robndbox>
        <angle>-11</angle>
    </object>
</annotation>
