<?xml version="1.0" encoding="UTF-8"?>
<annotation>
    <folder>/JPEGImages-test.zip/JPEGImages-test/JPEGImages-test</folder>
    <filename>14685.jpg</filename>
    <path>/JPEGImages-test.zip/JPEGImages-test/JPEGImages-test</path>
    <source>
        <database>Unknown</database>
    </source>
    <size>
        <width>800</width>
        <height>800</height>
        <depth>3</depth>
    </size>
    <segmented>0</segmented>
    <object>
        <type>robndbox</type>
        <name>stadium</name>
        <pose>Unspecified</pose>
        <truncated>0</truncated>
        <difficult>0</difficult>
        <robndbox>
            <x_left_top>417</x_left_top>
            <y_left_top>373</y_left_top>
            <x_right_top>578</x_right_top>
            <y_right_top>373</y_right_top>
            <x_right_bottom>578</x_right_bottom>
            <y_right_bottom>567</y_right_bottom>
            <x_left_bottom>417</x_left_bottom>
            <y_left_bottom>567</y_left_bottom>
        </robndbox>
        <angle>0</angle>
    </object>
    <object>
        <type>robndbox</type>
        <name>groundtrackfield</name>
        <pose>Unspecified</pose>
        <truncated>0</truncated>
        <difficult>0</difficult>
        <robndbox>
            <x_left_top>451</x_left_top>
            <y_left_top>392</y_left_top>
            <x_right_top>544</x_right_top>
            <y_right_top>392</y_right_top>
            <x_right_bottom>544</x_right_bottom>
            <y_right_bottom>549</y_right_bottom>
            <x_left_bottom>451</x_left_bottom>
            <y_left_bottom>549</y_left_bottom>
        </robndbox>
        <angle>0</angle>
    </object>
    <object>
        <type>robndbox</type>
        <name>overpass</name>
        <pose>Unspecified</pose>
        <truncated>0</truncated>
        <difficult>0</difficult>
        <robndbox>
            <x_left_top>330</x_left_top>
            <y_left_top>657</y_left_top>
            <x_right_top>337</x_right_top>
            <y_right_top>664</y_right_top>
            <x_right_bottom>318</x_right_bottom>
            <y_right_bottom>684</y_right_bottom>
            <x_left_bottom>311</x_left_bottom>
            <y_left_bottom>677</y_left_bottom>
        </robndbox>
        <angle>43.6</angle>
    </object>
    <object>
        <type>robndbox</type>
        <name>trainstation</name>
        <pose>Unspecified</pose>
        <truncated>0</truncated>
        <difficult>0</difficult>
        <robndbox>
            <x_left_top>72</x_left_top>
            <y_left_top>139</y_left_top>
            <x_right_top>599</x_right_top>
            <y_right_top>79</y_right_top>
            <x_right_bottom>608</x_right_bottom>
            <y_right_bottom>158</y_right_bottom>
            <x_left_bottom>81</x_left_bottom>
            <y_left_bottom>219</y_left_bottom>
        </robndbox>
        <angle>-6.6</angle>
    </object>
</annotation>
