<?xml version="1.0" encoding="UTF-8"?>
<annotation>
    <folder>/JPEGImages-test.zip/JPEGImages-test/JPEGImages-test</folder>
    <filename>15825.jpg</filename>
    <path>/JPEGImages-test.zip/JPEGImages-test/JPEGImages-test</path>
    <source>
        <database>Unknown</database>
    </source>
    <size>
        <width>800</width>
        <height>800</height>
        <depth>3</depth>
    </size>
    <segmented>0</segmented>
    <object>
        <type>robndbox</type>
        <name>vehicle</name>
        <pose>Unspecified</pose>
        <truncated>0</truncated>
        <difficult>0</difficult>
        <robndbox>
            <x_left_top>566</x_left_top>
            <y_left_top>47</y_left_top>
            <x_right_top>593</x_right_top>
            <y_right_top>53</y_right_top>
            <x_right_bottom>579</x_right_bottom>
            <y_right_bottom>125</y_right_bottom>
            <x_left_bottom>552</x_left_bottom>
            <y_left_bottom>119</y_left_bottom>
        </robndbox>
        <angle>11</angle>
    </object>
    <object>
        <type>robndbox</type>
        <name>vehicle</name>
        <pose>Unspecified</pose>
        <truncated>0</truncated>
        <difficult>0</difficult>
        <robndbox>
            <x_left_top>510</x_left_top>
            <y_left_top>309</y_left_top>
            <x_right_top>535</x_right_top>
            <y_right_top>314</y_right_top>
            <x_right_bottom>522</x_right_bottom>
            <y_right_bottom>376</y_right_bottom>
            <x_left_bottom>498</x_left_bottom>
            <y_left_bottom>372</y_left_bottom>
        </robndbox>
        <angle>11</angle>
    </object>
    <object>
        <type>robndbox</type>
        <name>vehicle</name>
        <pose>Unspecified</pose>
        <truncated>0</truncated>
        <difficult>0</difficult>
        <robndbox>
            <x_left_top>405</x_left_top>
            <y_left_top>256</y_left_top>
            <x_right_top>436</x_right_top>
            <y_right_top>262</y_right_top>
            <x_right_bottom>421</x_right_bottom>
            <y_right_bottom>338</y_right_bottom>
            <x_left_bottom>390</x_left_bottom>
            <y_left_bottom>332</y_left_bottom>
        </robndbox>
        <angle>11</angle>
    </object>
    <object>
        <type>robndbox</type>
        <name>vehicle</name>
        <pose>Unspecified</pose>
        <truncated>0</truncated>
        <difficult>0</difficult>
        <robndbox>
            <x_left_top>350</x_left_top>
            <y_left_top>306</y_left_top>
            <x_right_top>383</x_right_top>
            <y_right_top>314</y_right_top>
            <x_right_bottom>366</x_right_bottom>
            <y_right_bottom>382</y_right_bottom>
            <x_left_bottom>334</x_left_bottom>
            <y_left_bottom>373</y_left_bottom>
        </robndbox>
        <angle>13.8</angle>
    </object>
    <object>
        <type>robndbox</type>
        <name>vehicle</name>
        <pose>Unspecified</pose>
        <truncated>0</truncated>
        <difficult>0</difficult>
        <robndbox>
            <x_left_top>330</x_left_top>
            <y_left_top>603</y_left_top>
            <x_right_top>366</x_right_top>
            <y_right_top>612</y_right_top>
            <x_right_bottom>349</x_right_bottom>
            <y_right_bottom>688</y_right_bottom>
            <x_left_bottom>312</x_left_bottom>
            <y_left_bottom>680</y_left_bottom>
        </robndbox>
        <angle>12.8</angle>
    </object>
    <object>
        <type>robndbox</type>
        <name>vehicle</name>
        <pose>Unspecified</pose>
        <truncated>0</truncated>
        <difficult>0</difficult>
        <robndbox>
            <x_left_top>449</x_left_top>
            <y_left_top>673</y_left_top>
            <x_right_top>482</x_right_top>
            <y_right_top>679</y_right_top>
            <x_right_bottom>469</x_right_bottom>
            <y_right_bottom>746</y_right_bottom>
            <x_left_bottom>437</x_left_bottom>
            <y_left_bottom>740</y_left_bottom>
        </robndbox>
        <angle>10.6</angle>
    </object>
</annotation>
