<?xml version="1.0" encoding="UTF-8"?>
<annotation>
    <folder>/JPEGImages-test.zip/JPEGImages-test/JPEGImages-test</folder>
    <filename>18059.jpg</filename>
    <path>/JPEGImages-test.zip/JPEGImages-test/JPEGImages-test</path>
    <source>
        <database>Unknown</database>
    </source>
    <size>
        <width>800</width>
        <height>800</height>
        <depth>3</depth>
    </size>
    <segmented>0</segmented>
    <object>
        <type>robndbox</type>
        <name>baseballfield</name>
        <pose>Unspecified</pose>
        <truncated>0</truncated>
        <difficult>0</difficult>
        <robndbox>
            <x_left_top>176</x_left_top>
            <y_left_top>145</y_left_top>
            <x_right_top>207</x_right_top>
            <y_right_top>161</y_right_top>
            <x_right_bottom>194</x_right_bottom>
            <y_right_bottom>187</y_right_bottom>
            <x_left_bottom>162</x_left_bottom>
            <y_left_bottom>171</y_left_bottom>
        </robndbox>
        <angle>27.6</angle>
    </object>
    <object>
        <type>robndbox</type>
        <name>baseballfield</name>
        <pose>Unspecified</pose>
        <truncated>0</truncated>
        <difficult>0</difficult>
        <robndbox>
            <x_left_top>162</x_left_top>
            <y_left_top>174</y_left_top>
            <x_right_top>190</x_right_top>
            <y_right_top>189</y_right_top>
            <x_right_bottom>176</x_right_bottom>
            <y_right_bottom>216</y_right_bottom>
            <x_left_bottom>147</x_left_bottom>
            <y_left_bottom>201</y_left_bottom>
        </robndbox>
        <angle>27.6</angle>
    </object>
    <object>
        <type>robndbox</type>
        <name>groundtrackfield</name>
        <pose>Unspecified</pose>
        <truncated>0</truncated>
        <difficult>0</difficult>
        <robndbox>
            <x_left_top>258</x_left_top>
            <y_left_top>107</y_left_top>
            <x_right_top>309</x_right_top>
            <y_right_top>134</y_right_top>
            <x_right_bottom>262</x_right_bottom>
            <y_right_bottom>225</y_right_bottom>
            <x_left_bottom>210</x_left_bottom>
            <y_left_bottom>198</y_left_bottom>
        </robndbox>
        <angle>27.6</angle>
    </object>
    <object>
        <type>robndbox</type>
        <name>baseballfield</name>
        <pose>Unspecified</pose>
        <truncated>0</truncated>
        <difficult>0</difficult>
        <robndbox>
            <x_left_top>528</x_left_top>
            <y_left_top>526</y_left_top>
            <x_right_top>544</x_right_top>
            <y_right_top>542</y_right_top>
            <x_right_bottom>529</x_right_bottom>
            <y_right_bottom>557</y_right_bottom>
            <x_left_bottom>513</x_left_bottom>
            <y_left_bottom>541</y_left_bottom>
        </robndbox>
        <angle>45</angle>
    </object>
</annotation>
